[{"line":1,"elements":[{"start_timestamp":"2023-02-09T02:51:29.476Z","before":[{"result":{"duration":2085434900,"status":"passed"},"match":{"location":"tek.sdet.framework.base.BaseUITest.setupTests()"}}],"line":4,"name":"Verify user can search a product","description":"","id":"this-feature-is-use-for-testing-ui-of-retail-page;verify-user-can-search-a-product","after":[{"result":{"duration":135636900,"status":"passed"},"match":{"location":"tek.sdet.framework.base.BaseUITest.closeTests(io.cucumber.java.Scenario)"}}],"type":"scenario","keyword":"Scenario","steps":[{"result":{"duration":61950300,"status":"passed"},"line":5,"name":"User is on retail website","match":{"location":"tek.sdet.framework.steps.RetailSteps.userIsOnRetailWebsite()"},"keyword":"Given "},{"result":{"duration":205981300,"status":"passed"},"line":6,"name":"User search for \"pokemon\" product","match":{"arguments":[{"val":"\"pokemon\"","offset":16}],"location":"tek.sdet.framework.steps.RetailSteps.userSearchForProduct(java.lang.String)"},"keyword":"When "},{"result":{"duration":82777900,"status":"passed"},"line":7,"name":"The product should be displayed","match":{"location":"tek.sdet.framework.steps.RetailSteps.theProductShouldBeDisplayed()"},"keyword":"Then "}],"tags":[{"name":"@test"}]}],"name":"This feature is use for testing UI of Retail page","description":"","id":"this-feature-is-use-for-testing-ui-of-retail-page","keyword":"Feature","uri":"classpath:features/retail.feature","tags":[]}]